nproc/__init__.py
nproc/npc.py
nproc-1.5.2.dist-info/LICENSE
nproc-1.5.2.dist-info/METADATA
nproc-1.5.2.dist-info/WHEEL
nproc-1.5.2.dist-info/top_level.txt
nproc-1.5.2.dist-info/RECORD
