Metadata-Version: 2.1
Name: nproc
Version: 1.5.2
Summary: Neyman-Pearson (NP) Classification Algorithms and NP Receiver Operating Characteristic (NP-ROC) Curves
Home-page: https://github.com/ZhaoRichard/nproc
Author: Richard Zhao, Yang Feng, Jingyi Jessica Li and Xin Tong
Author-email: zhao.rich@gmail.com
License: UNKNOWN
Platform: UNKNOWN
License-File: LICENSE
Requires-Dist: scipy
Requires-Dist: sklearn
Requires-Dist: numpy
Requires-Dist: joblib
